graph/__init__.py
graph/admin.py
graph/apps.py
graph/csv_parser.py
graph/forms.py
graph/graph_lib.py
graph/image_builder.py
graph/models.py
graph/tests.py
graph/urls.py
graph/views.py
netview/__init__.py
netview/asgi.py
netview/settings.py
netview/urls.py
netview/wsgi.py
sample/init.py
sample/run.py
templates/graph_base.html
templates/icons.html
templates/index.html
templates/sidebar_base.html
templates/sidebar_context.html
templates/sidebar_form.html
templates/upload_base.html
NetView-1.12.dist-info/METADATA
NetView-1.12.dist-info/WHEEL
NetView-1.12.dist-info/entry_points.txt
NetView-1.12.dist-info/top_level.txt
NetView-1.12.dist-info/RECORD
