Metadata-Version: 2.1
Name: NetView
Version: 1.12
Summary: Network Grapher
Home-page: https://github.com/danielgiampaolo/CIS4930_Python
Author: CIS4930 NetView Team
Author-email: adrian.salazar@ufl.edu
License: UNKNOWN
Platform: UNKNOWN
Requires-Dist: networkx
Requires-Dist: Django
Requires-Dist: matplotlib
